{
	"data": 
		{
			"data/image/icon.png": 
				{
					"name": "data/image/icon.png",
					"MD5": "1ff3c15983db06052ec3ae0bb5edb003",
					"size": 633
				},
			"data/image/loading.png": 
				{
					"name": "data/image/loading.png",
					"MD5": "f42f1ffb55a48414be7cc0d8e1992204",
					"size": 776
				},
			"data/scene/launch.scene": 
				{
					"name": "data/scene/launch.scene",
					"MD5": "2a9163ed31d56e5a8a4956298ef34320",
					"size": 132
				},
			"data/ui/canvas.prefab": 
				{
					"name": "data/ui/canvas.prefab",
					"MD5": "1c7cc0f3d2345a833dab923993cbd150",
					"size": 6
				}
		}
}